setup.py
pyelectron/__init__.py
pyelectron.egg-info/PKG-INFO
pyelectron.egg-info/SOURCES.txt
pyelectron.egg-info/dependency_links.txt
pyelectron.egg-info/not-zip-safe
pyelectron.egg-info/top_level.txt