Metadata-Version: 1.1
Name: pyelectron
Version: 1.0
Summary: Make desktop app with html5 and JS using python and pytron
Home-page: http://github.com/nishowsan/python-electron
Author: Adib Mohsin
Author-email: md.nishow@gmail.com
License: MIT
Platform: UNKNOWN
Requires: pyqt5
